repo_on_fire-0.2.5.dist-info/METADATA
repo_on_fire-0.2.5.dist-info/WHEEL
repo_on_fire-0.2.5.dist-info/entry_points.txt
repo_on_fire-0.2.5.dist-info/licenses/COPYING
repo_on_fire-0.2.5.dist-info/licenses/COPYING.LESSER
repo_on_fire/__init__.py
repo_on_fire/__main__.py
repo_on_fire/_locks.py
repo_on_fire/_workspace_helper.py
repo_on_fire/application.py
repo_on_fire/cli.py
repo_on_fire/configuration.py
repo_on_fire/constants.py
repo_on_fire/exceptions.py
repo_on_fire/repo.py
repo_on_fire/workspace.py
repo_on_fire-0.2.5.dist-info/RECORD
