Metadata-Version: 2.1
Name: repo-on-fire
Version: 0.2.5
Summary: A thin wrapper around Google's repo tool, adding some extras on top!
Author-Email: Martin Hoeher <martin@rpdev.net>
License: LGPL-3.0-or-later
Classifier: Programming Language :: Python :: 3
Classifier: Operating System :: OS Independent
Classifier: Programming Language :: Python :: 3 :: Only
Classifier: Programming Language :: Python :: 3.8
Classifier: Programming Language :: Python :: 3.9
Classifier: Programming Language :: Python :: 3.10
Classifier: Programming Language :: Python :: 3.11
Classifier: Programming Language :: Python :: 3.12
Project-URL: Homepage, https://gitlab.com/rpdev/repo-on-fire
Project-URL: Documentation, https://repo-on-fire.readthedocs.io/en/latest/
Project-URL: Bug Tracker, https://gitlab.com/rpdev/repo-on-fire/-/issues
Requires-Python: <4.0,>=3.8
Requires-Dist: pydantic>=2.6.1
Requires-Dist: pydantic-settings>=2.1.0
Requires-Dist: flufl-lock>=8.0.2
Requires-Dist: appdirs>=1.4.4
Requires-Dist: requests>=2.31.0
Requires-Dist: tomlkit>=0.12.3
Requires-Dist: click>=8.1.7
